data_structures_jyen/__init__.py
data_structures_jyen/array.py
data_structures_jyen/graph.py
data_structures_jyen/linked_list.py
data_structures_jyen/queue.py
data_structures_jyen/stack.py
data_structures_jyen/tree.py
jyen_data_structure-0.1.3.dist-info/licenses/LICENCE
jyen_data_structure-0.1.3.dist-info/METADATA
jyen_data_structure-0.1.3.dist-info/WHEEL
jyen_data_structure-0.1.3.dist-info/top_level.txt
jyen_data_structure-0.1.3.dist-info/RECORD
