Metadata-Version: 2.4
Name: jyen-data-structure
Version: 0.1.3
Summary: A Python package implementing fundamental data structures such as arrays, stacks, queues, linked lists, graphs, and trees.
Author-email: Joshua Juste Emmanuel Yun Pei NIKIEMA <joshuanikiema24@gmail.com>
License: # Copyright (c) 2018 The Python Packaging Authority
Project-URL: Homepage, https://github.com/Yunpei24/data_structures_jyen
Project-URL: Documentation, https://yunpei24.github.io/data_structures_jyen
Project-URL: Bug Tracker, https://github.com/Yunpei24/data_structures_jyen/issues
Keywords: data structures,python,educational,stack,queue,graph,tree,linked list,array
Classifier: Programming Language :: Python :: 3
Classifier: License :: OSI Approved :: MIT License
Classifier: Operating System :: OS Independent
Classifier: Intended Audience :: Education
Classifier: Topic :: Software Development :: Libraries :: Python Modules
Requires-Python: >=3.8
License-File: LICENCE
Dynamic: license-file
